Metadata-Version: 2.1
Name: aihabitat-lab
Version: 0.2.4.dev20230331
Summary: Habitat-Lab: a modular high-level library for end-to-end development in Embodied AI.
Home-page: https://aihabitat.org
Author: Meta AI Research
License: MIT License
Project-URL: GitHub repo, https://github.com/facebookresearch/habitat-lab/
Project-URL: Bug Tracker, https://github.com/facebookresearch/habitat-lab/issues
Classifier: Intended Audience :: Science/Research
Classifier: Development Status :: 5 - Production/Stable
Classifier: License :: OSI Approved :: MIT License
Classifier: Topic :: Scientific/Engineering :: Artificial Intelligence
Classifier: Programming Language :: Python
Classifier: Programming Language :: Python :: 3
Classifier: Programming Language :: Python :: 3.9
Classifier: Programming Language :: Python :: 3.10
Classifier: Programming Language :: Python :: 3.11
Classifier: Intended Audience :: Developers
Classifier: Intended Audience :: Education
Classifier: Intended Audience :: Science/Research
Classifier: Operating System :: MacOS
Classifier: Operating System :: Unix
Requires-Dist: gym (<0.23.1,>=0.22.0)
Requires-Dist: numpy (>=1.20.0)
Requires-Dist: numpy-quaternion (>=2019.3.18.14.33.20)
Requires-Dist: attrs (>=19.1.0)
Requires-Dist: opencv-python (>=3.3.0)
Requires-Dist: hydra-core (>=1.2.0)
Requires-Dist: omegaconf (>=2.2.3)
Requires-Dist: numba (>=0.44.0)
Requires-Dist: imageio (>=2.2.0)
Requires-Dist: imageio-ffmpeg (>=0.2.0)
Requires-Dist: scipy (>=1.0.0)
Requires-Dist: tqdm (>=4.0.0)
Requires-Dist: pickle5 ; python_version < "3.8"
